{
  "title": "Rostrum [CTImageSeries] [CT]",
  "detail_url": "https://www.morphosource.org/concern/media/000721807?locale=en",
  "id": "000721807",
  "Object": "AMNH:FARB:24444",
  "Taxonomy": "Brasileodactylus araripensis",
  "Element or Part": "rostrum",
  "Modality": "X-Ray Computed Tomography (CT/microCT)",
  "Data Manager": "American Museum of Natural History - AMNH Vertebrate Paleontology Collection",
  "Date Uploaded": "03/18/2025",
  "Publication Status": "Restricted Download",
  "Rights Statement": "In Copyright"
}